certificate_generator/__init__.py
certificate_generator/generator.py
certificate_generator/src/GreatVibes-Regular.ttf
certificate_generator/src/logo.png
certificate_generator/src/template2.png
certificate_generator-0.3.dist-info/LICENSE
certificate_generator-0.3.dist-info/METADATA
certificate_generator-0.3.dist-info/WHEEL
certificate_generator-0.3.dist-info/entry_points.txt
certificate_generator-0.3.dist-info/top_level.txt
certificate_generator-0.3.dist-info/RECORD
