Metadata-Version: 2.1
Name: certificate_generator
Version: 0.3
Summary: A package to generate certificates with a given name and a logo in the top middle.
Home-page: https://github.com/codewithasib/certificate_generator
Author: Asib Hossen
Author-email: dev.asib@proton.me
Classifier: Programming Language :: Python :: 3
Classifier: License :: OSI Approved :: MIT License
Classifier: Operating System :: OS Independent
Requires-Python: >=3.6
License-File: LICENSE
Requires-Dist: Pillow
